llamahelper/__init__.py
llamahelper/core.py
llamahelper/log.py
llamahelper/server.py
llamahelper/store_utils.py
llamahelper/utils.py
llamahelper/factory/__init__.py
llamahelper/factory/agent.py
llamahelper/factory/cleaner.py
llamahelper/factory/embedding.py
llamahelper/factory/extractor.py
llamahelper/factory/graph_extractor.py
llamahelper/factory/index.py
llamahelper/factory/llms.py
llamahelper/factory/node_parser.py
llamahelper/factory/postprocessor.py
llamahelper/factory/reader.py
llamahelper/factory/retriver.py
llamahelper/factory/splitter.py
llamahelper/factory/store.py
llamahelper/querypipz/__init__.py
llamahelper/querypipz/abc_.py
llamahelper/querypipz/director.py
llamahelper/querypipz/query_pipeline.py
llamahelper/querypipz/queryer.py
llamahelper/querypipz/utils.py
llamahelper/querypipz/builder/__init__.py
llamahelper/querypipz/builder/builderlib.py
llamahelper-0.1.6.dist-info/METADATA
llamahelper-0.1.6.dist-info/WHEEL
llamahelper-0.1.6.dist-info/top_level.txt
llamahelper-0.1.6.dist-info/RECORD
