Metadata-Version: 2.4
Name: llamahelper
Version: 0.1.6
Summary: Add your description here
Requires-Python: >=3.12
Requires-Dist: anyio>=4.11.0
Requires-Dist: fastapi>=0.118.1
Requires-Dist: llama-index>=0.12.30
Requires-Dist: llama-index-tools-mcp>=0.4.1
Requires-Dist: llmada>=1.0.3
Requires-Dist: pypdf>=6.1.1
Requires-Dist: pypdf2>=3.0.1
Requires-Dist: pytest>=8.4.2
Requires-Dist: pytest-asyncio>=1.2.0
Requires-Dist: pytest-tornasync>=0.6.0.post2
Requires-Dist: toml>=0.10.2
Requires-Dist: utils-tool>=0.1.4
Requires-Dist: uvicorn>=0.37.0
Requires-Dist: volcengine-python-sdk==4.0.6
